grblhud/__init__.py
grblhud/__main__.py
grblhud/grblbuffer.py
grblhud/grblhudloop.py
grblhud/grblmessages.py
grblhud/lineinput.py
grblhud/unblockedgetch.py
grblhud-1.7.11.dist-info/entry_points.txt
grblhud-1.7.11.dist-info/licenses/LICENSE
grblhud-1.7.11.dist-info/WHEEL
grblhud-1.7.11.dist-info/METADATA
grblhud-1.7.11.dist-info/RECORD
