Metadata-Version: 2.4
Name: grblhud
Version: 1.7.11
Summary: grblhub: a command line tool to handle grbl code.
Keywords: grbl,grblv1.1,hud,laser cutter,laser engraving
Author-email: Johannes Noordanus <mailjohannes.mailnoordanus@gmail.com>
Requires-Python: >=3.7
Classifier: License :: OSI Approved :: MIT License
License-File: LICENSE
Requires-Dist: inputimeout >= 1.0.4
Requires-Dist: pyserial >= 3.5
Project-URL: Home, https://github.com/johannesnoordanus/grblhud
